{
    "H01": {
        "ACT": "0",
        "ATR": "Honors and S General Education and Upper Division",
        "CAP": "5",
        "CMP": "PWL",
        "CRD": "3.000",
        "CRN": "11065",
        "CRS": "49800",
        "DAY": " ",
        "DTE": "08/20-12/08",
        "INS": "Michele R Buzon (P)",
        "LKS": " ",
        "LOC": "TBA",
        "NTS": " ",
        "REM": "5",
        "REQ": "",
        "SBJ": "ANTH",
        "SEC": "H01",
        "TME": "TBA",
        "TTL": "Senior Honors Paper",
        "TYP": "Individual Study"
    },
    "H02": {
        "ACT": "0",
        "ATR": "Honors and S General Education and Upper Division",
        "CAP": "5",
        "CMP": "PWL",
        "CRD": "3.000",
        "CRN": "59808",
        "CRS": "49800",
        "DAY": " ",
        "DTE": "08/20-12/08",
        "INS": "Sherylyn H Briller (P)",
        "LKS": " ",
        "LOC": "TBA",
        "NTS": " ",
        "REM": "5",
        "REQ": "",
        "SBJ": "ANTH",
        "SEC": "H02",
        "TME": "TBA",
        "TTL": "Senior Honors Paper",
        "TYP": "Individual Study"
    }
}