{
    "001": {
        "ACT": "119",
        "ATR": "Dept Credit and Lower Division and GTC-Social-Behavioral and GTC-Information Literacy and UC-Information Literacy and UC-Behavior/Social Science",
        "CAP": "120",
        "CMP": "PWL",
        "CRD": "3.000",
        "CRN": "10674",
        "CRS": "20100",
        "DAY": "TR",
        "DTE": "08/20-12/08",
        "INS": "Pamala Victoria Morris (P)",
        "LKS": "A1|A2",
        "LOC": "WALC 3087",
        "NTS": " ",
        "REM": "1",
        "REQ": " ",
        "SBJ": "AGR",
        "SEC": "001",
        "TME": "09:30 am-10:20 am",
        "TTL": "Communicating Across Culture",
        "TYP": "Lecture"
    },
    "002": {
        "ACT": "20",
        "ATR": "Dept Credit and Lower Division and GTC-Social-Behavioral and GTC-Information Literacy and UC-Information Literacy and UC-Behavior/Social Science",
        "CAP": "20",
        "CMP": "PWL",
        "CRD": "0.000",
        "CRN": "10675",
        "CRS": "20100",
        "DAY": "W",
        "DTE": "08/20-12/08",
        "INS": "Adegoke A Adetunji (P)",
        "LKS": "A2|A1",
        "LOC": "LILY 3102",
        "NTS": " ",
        "REM": "0",
        "REQ": " ",
        "SBJ": "AGR",
        "SEC": "002",
        "TME": "09:30 am-11:20 am",
        "TTL": "Communicating Across Culture",
        "TYP": "Laboratory"
    },
    "003": {
        "ACT": "20",
        "ATR": "Dept Credit and Lower Division and GTC-Social-Behavioral and GTC-Information Literacy and UC-Information Literacy and UC-Behavior/Social Science",
        "CAP": "20",
        "CMP": "PWL",
        "CRD": "0.000",
        "CRN": "10676",
        "CRS": "20100",
        "DAY": "W",
        "DTE": "08/20-12/08",
        "INS": "Janelle A Cronin (P)",
        "LKS": "A2|A1",
        "LOC": "LILY 3102",
        "NTS": " ",
        "REM": "0",
        "REQ": " ",
        "SBJ": "AGR",
        "SEC": "003",
        "TME": "11:30 am-01:20 pm",
        "TTL": "Communicating Across Culture",
        "TYP": "Laboratory"
    },
    "004": {
        "ACT": "20",
        "ATR": "Dept Credit and Lower Division and GTC-Social-Behavioral and GTC-Information Literacy and UC-Information Literacy and UC-Behavior/Social Science",
        "CAP": "20",
        "CMP": "PWL",
        "CRD": "0.000",
        "CRN": "10677",
        "CRS": "20100",
        "DAY": "W",
        "DTE": "08/20-12/08",
        "INS": "Asmaa Hamed Morsi (P)",
        "LKS": "A2|A1",
        "LOC": "NLSN 1215",
        "NTS": " ",
        "REM": "0",
        "REQ": " ",
        "SBJ": "AGR",
        "SEC": "004",
        "TME": "01:30 pm-03:20 pm",
        "TTL": "Communicating Across Culture",
        "TYP": "Laboratory"
    },
    "005": {
        "ACT": "20",
        "ATR": "Dept Credit and Lower Division and GTC-Social-Behavioral and GTC-Information Literacy and UC-Information Literacy and UC-Behavior/Social Science",
        "CAP": "20",
        "CMP": "PWL",
        "CRD": "0.000",
        "CRN": "10678",
        "CRS": "20100",
        "DAY": "F",
        "DTE": "08/20-12/08",
        "INS": "Miranda E Furrer (P)",
        "LKS": "A2|A1",
        "LOC": "LILY 3102",
        "NTS": " ",
        "REM": "0",
        "REQ": " ",
        "SBJ": "AGR",
        "SEC": "005",
        "TME": "09:30 am-11:20 am",
        "TTL": "Communicating Across Culture",
        "TYP": "Laboratory"
    },
    "006": {
        "ACT": "20",
        "ATR": "Dept Credit and Lower Division and GTC-Social-Behavioral and GTC-Information Literacy and UC-Information Literacy and UC-Behavior/Social Science",
        "CAP": "20",
        "CMP": "PWL",
        "CRD": "0.000",
        "CRN": "10679",
        "CRS": "20100",
        "DAY": "F",
        "DTE": "08/20-12/08",
        "INS": "Asmaa Hamed Morsi (P)",
        "LKS": "A2|A1",
        "LOC": "LILY 3102",
        "NTS": " ",
        "REM": "0",
        "REQ": " ",
        "SBJ": "AGR",
        "SEC": "006",
        "TME": "11:30 am-01:20 pm",
        "TTL": "Communicating Across Culture",
        "TYP": "Laboratory"
    },
    "007": {
        "ACT": "19",
        "ATR": "Dept Credit and Lower Division and GTC-Social-Behavioral and GTC-Information Literacy and UC-Information Literacy and UC-Behavior/Social Science",
        "CAP": "20",
        "CMP": "PWL",
        "CRD": "0.000",
        "CRN": "10680",
        "CRS": "20100",
        "DAY": "F",
        "DTE": "08/20-12/08",
        "INS": "Adegoke A Adetunji (P)",
        "LKS": "A2|A1",
        "LOC": "NLSN 1215",
        "NTS": " ",
        "REM": "1",
        "REQ": " ",
        "SBJ": "AGR",
        "SEC": "007",
        "TME": "01:30 pm-03:20 pm",
        "TTL": "Communicating Across Culture",
        "TYP": "Laboratory"
    },
    "Y01": {
        "ACT": "48",
        "ATR": "Dept Credit and Lower Division and GTC-Social-Behavioral and GTC-Information Literacy and UC-Information Literacy and UC-Behavior/Social Science",
        "CAP": "44",
        "CMP": "PWL",
        "CRD": "3.000",
        "CRN": "54639",
        "CRS": "20100",
        "DAY": " ",
        "DTE": "08/20-12/08",
        "INS": "Pamala Victoria Morris (P)",
        "LKS": " ",
        "LOC": "TBA",
        "NTS": " ",
        "REM": "-4",
        "REQ": " ",
        "SBJ": "AGR",
        "SEC": "Y01",
        "TME": "TBA",
        "TTL": "Communicating Across Culture",
        "TYP": "Distance Learning"
    }
}