{
    "001": {
        "ACT": "29",
        "ATR": "Upper Division",
        "CAP": "28",
        "CMP": "PWL",
        "CRD": "3.000",
        "CRN": "10814",
        "CRS": "56500",
        "DAY": "MW",
        "DTE": "08/20-12/08",
        "INS": "Darrell G Schulze (P)",
        "LKS": "A1|A2",
        "LOC": "LILY 3409",
        "NTS": " ",
        "REM": "-1",
        "REQ": "",
        "SBJ": "AGRY",
        "SEC": "001",
        "TME": "10:30 am-11:20 am",
        "TTL": "Soils And Landscapes",
        "TYP": "Lecture"
    },
    "002": {
        "ACT": "29",
        "ATR": "Upper Division",
        "CAP": "28",
        "CMP": "PWL",
        "CRD": "0.000",
        "CRN": "10815",
        "CRS": "56500",
        "DAY": "W",
        "DTE": "08/20-12/08",
        "INS": "Joshua Okach Minai (P), Darrell G Schulze",
        "LKS": "A2|A1",
        "LOC": "LILY 3409",
        "NTS": " ",
        "REM": "-1",
        "REQ": "",
        "SBJ": "AGRY",
        "SEC": "002",
        "TME": "02:30 pm-05:20 pm",
        "TTL": "Soils And Landscapes",
        "TYP": "Laboratory"
    }
}