{
    "PEO": {
        "ACT": "11",
        "ATR": "Upper Division",
        "CAP": "95",
        "CMP": "CEC",
        "CRD": "3.000",
        "CRN": "16655",
        "CRS": "55300",
        "DAY": " ",
        "DTE": "08/20-12/08",
        "INS": "Tyler N Tallman (P)",
        "LKS": " ",
        "LOC": "TBA",
        "NTS": "\"Students registering for this course must be pre-registered as a distance student with Engineering Professional Education (https://engineering.purdue.edu/ProEd/register/login_credit).\"",
        "REM": "84",
        "REQ": "",
        "SBJ": "AAE",
        "SEC": "PEO",
        "TME": "TBA",
        "TTL": "Elasticity In Aerospace Engineering",
        "TYP": "Distance Learning"
    },
    "WNG": {
        "ACT": "30",
        "ATR": "Upper Division",
        "CAP": "45",
        "CMP": "PWL",
        "CRD": "3.000",
        "CRN": "10084",
        "CRS": "55300",
        "DAY": "TR",
        "DTE": "08/20-12/08",
        "INS": "Tyler N Tallman (P)",
        "LKS": " ",
        "LOC": "WANG 2579",
        "NTS": " ",
        "REM": "15",
        "REQ": "",
        "SBJ": "AAE",
        "SEC": "WNG",
        "TME": "03:00 pm-04:15 pm",
        "TTL": "Elasticity In Aerospace Engineering",
        "TYP": "Lecture"
    }
}